bthlabs_jsonrpc_core/__init__.py
bthlabs_jsonrpc_core/decorators.py
bthlabs_jsonrpc_core/exceptions.py
bthlabs_jsonrpc_core/executor.py
bthlabs_jsonrpc_core/registry.py
bthlabs_jsonrpc_core/serializer.py
bthlabs_jsonrpc_core-1.0.0.dist-info/LICENSE
bthlabs_jsonrpc_core-1.0.0.dist-info/WHEEL
bthlabs_jsonrpc_core-1.0.0.dist-info/METADATA
bthlabs_jsonrpc_core-1.0.0.dist-info/RECORD
